SybilChecks/__init__.py
SybilChecks/checks.py
SybilChecks-0.0.6.dist-info/LICENSE
SybilChecks-0.0.6.dist-info/METADATA
SybilChecks-0.0.6.dist-info/WHEEL
SybilChecks-0.0.6.dist-info/top_level.txt
SybilChecks-0.0.6.dist-info/RECORD
