Metadata-Version: 2.1
Name: SybilChecks
Version: 0.0.6
Summary: make first and simple checks for wallets trasactional relations to grantees/donnors on public funding rounds onchain
Home-page: https://github.com/stefi-says/web3_projects_and_contributions/tree/main/sybil_start_checks_package
Author: Stefani P
Author-email: vieiraste@gmail.com
Classifier: Programming Language :: Python :: 3
Classifier: License :: OSI Approved :: MIT License
Classifier: Operating System :: OS Independent
Requires-Python: >=3.7
License-File: LICENSE
